{
  "_description": "Maps hardcoded hex colors to CSS variable tokens. Based on styles/tokens/colors.css",
  "_usage": "Used by scripts/fix-hardcoded-colors.mjs to automatically replace hardcoded colors",
  
  "mappings": {
    "backgrounds": {
      "#0d1b2a": "var(--color-bg-base, #0d1b2a)",
      "#1b263b": "var(--color-bg-elevated, #1b263b)",
      "#1a2332": "var(--color-bg-elevated, #1a2332)",
      "#111827": "var(--color-bg-base, #111827)",
      "#0a1628": "var(--color-bg-base, #0a1628)",
      "#000000": "var(--color-bg-base, #000000)",
      "#000": "var(--color-bg-base, #000000)"
    },
    
    "text": {
      "#ffffff": "var(--color-text-primary, #ffffff)",
      "#fff": "var(--color-text-primary, #ffffff)",
      "#94a3b8": "var(--color-text-secondary, #94a3b8)",
      "#64748b": "var(--color-text-tertiary, #64748b)",
      "#475569": "var(--color-text-muted, #475569)",
      "#334155": "var(--color-text-muted, #334155)",
      "#9ca3af": "var(--color-text-secondary, #9ca3af)",
      "#6b7280": "var(--color-text-tertiary, #6b7280)",
      "#4b5563": "var(--color-text-muted, #4b5563)",
      "#374151": "var(--color-text-muted, #374151)"
    },
    
    "accentLime": {
      "#d4ff00": "var(--color-accent-lime, #d4ff00)",
      "#bfe600": "var(--color-accent-lime-dark, #bfe600)",
      "#c8f000": "var(--color-accent-lime-dark, #c8f000)"
    },
    
    "accentTeal": {
      "#10b981": "var(--color-accent-teal, #10b981)",
      "#34d399": "var(--color-accent-teal-light, #34d399)",
      "#059669": "var(--color-accent-teal, #059669)",
      "#047857": "var(--color-accent-teal, #047857)",
      "#0d9488": "var(--color-accent-teal, #0d9488)",
      "#14b8a6": "var(--color-accent-teal-light, #14b8a6)"
    },
    
    "accentBlue": {
      "#3b82f6": "var(--color-accent-blue, #3b82f6)",
      "#60a5fa": "var(--color-accent-blue-light, #60a5fa)",
      "#2563eb": "var(--color-accent-blue, #2563eb)",
      "#1d4ed8": "var(--color-accent-blue, #1d4ed8)",
      "#93c5fd": "var(--color-accent-blue-light, #93c5fd)"
    },
    
    "accentAmber": {
      "#f59e0b": "var(--color-accent-amber, #f59e0b)",
      "#fbbf24": "var(--color-accent-amber-light, #fbbf24)",
      "#d97706": "var(--color-accent-amber, #d97706)",
      "#b45309": "var(--color-accent-amber, #b45309)"
    },
    
    "semantic": {
      "#22c55e": "var(--color-success, #22c55e)",
      "#16a34a": "var(--color-success, #16a34a)",
      "#15803d": "var(--color-success, #15803d)",
      "#ef4444": "var(--color-error, #ef4444)",
      "#dc2626": "var(--color-error, #dc2626)",
      "#b91c1c": "var(--color-error, #b91c1c)",
      "#f87171": "var(--color-error, #f87171)"
    },
    
    "borders": {
      "#e5e7eb": "var(--color-border-subtle, #e5e7eb)",
      "#d1d5db": "var(--color-border-default, #d1d5db)",
      "#9ca3af": "var(--color-border-strong, #9ca3af)"
    },
    
    "deprecated_gold": {
      "#d4a84b": "var(--color-accent-amber, #d4a84b)",
      "#c9a048": "var(--color-accent-amber, #c9a048)",
      "#b8962f": "var(--color-accent-amber, #b8962f)"
    }
  },
  
  "flatMap": {
    "#0d1b2a": "var(--color-bg-base, #0d1b2a)",
    "#1b263b": "var(--color-bg-elevated, #1b263b)",
    "#1a2332": "var(--color-bg-elevated, #1a2332)",
    "#111827": "var(--color-bg-base, #111827)",
    "#0a1628": "var(--color-bg-base, #0a1628)",
    "#000000": "var(--color-bg-base, #000000)",
    "#000": "var(--color-bg-base, #000000)",
    "#0f172a": "var(--color-bg-base, #0f172a)",
    "#0a0a0f": "var(--color-bg-base, #0a0a0f)",
    "#1a1d24": "var(--color-bg-base, #1a1d24)",
    "#1a1a1a": "var(--color-bg-base, #1a1a1a)",
    "#1e293b": "var(--color-bg-elevated, #1e293b)",
    "#1f2937": "var(--color-bg-elevated, #1f2937)",
    "#222222": "var(--color-bg-elevated, #222222)",
    "#333333": "var(--color-text-muted, #333333)",
    "#ffffff": "var(--color-text-primary, #ffffff)",
    "#fff": "var(--color-text-primary, #ffffff)",
    "#f8fafc": "var(--color-bg-muted, #f8fafc)",
    "#f9fafb": "var(--color-bg-muted, #f9fafb)",
    "#f3f4f6": "var(--color-bg-muted, #f3f4f6)",
    "#f1f5f9": "var(--color-bg-muted, #f1f5f9)",
    "#94a3b8": "var(--color-text-secondary, #94a3b8)",
    "#64748b": "var(--color-text-tertiary, #64748b)",
    "#475569": "var(--color-text-muted, #475569)",
    "#334155": "var(--color-text-muted, #334155)",
    "#9ca3af": "var(--color-text-secondary, #9ca3af)",
    "#6b7280": "var(--color-text-tertiary, #6b7280)",
    "#4b5563": "var(--color-text-muted, #4b5563)",
    "#374151": "var(--color-text-muted, #374151)",
    "#a1a1aa": "var(--color-text-muted, #a1a1aa)",
    "#999999": "var(--color-text-muted, #999999)",
    "#666666": "var(--color-text-muted, #666666)",
    "#555555": "var(--color-text-muted, #555555)",
    "#cccccc": "var(--color-text-secondary, #cccccc)",
    "#d4ff00": "var(--color-accent-lime, #d4ff00)",
    "#bfe600": "var(--color-accent-lime-dark, #bfe600)",
    "#c8f000": "var(--color-accent-lime-dark, #c8f000)",
    "#10b981": "var(--color-accent-teal, #10b981)",
    "#34d399": "var(--color-accent-teal-light, #34d399)",
    "#059669": "var(--color-accent-teal, #059669)",
    "#047857": "var(--color-accent-teal, #047857)",
    "#0d9488": "var(--color-accent-teal, #0d9488)",
    "#14b8a6": "var(--color-accent-teal-light, #14b8a6)",
    "#0d9668": "var(--color-accent-teal, #0d9668)",
    "#0ea472": "var(--color-accent-teal, #0ea472)",
    "#06b6d4": "var(--color-accent-teal, #06b6d4)",
    "#3b82f6": "var(--color-accent-blue, #3b82f6)",
    "#60a5fa": "var(--color-accent-blue-light, #60a5fa)",
    "#2563eb": "var(--color-accent-blue, #2563eb)",
    "#1d4ed8": "var(--color-accent-blue, #1d4ed8)",
    "#93c5fd": "var(--color-accent-blue-light, #93c5fd)",
    "#a5b4fc": "var(--color-accent-blue-light, #a5b4fc)",
    "#5ba3d0": "var(--color-accent-blue-light, #5ba3d0)",
    "#1a4d6e": "var(--color-accent-blue, #1a4d6e)",
    "#f59e0b": "var(--color-accent-amber, #f59e0b)",
    "#fbbf24": "var(--color-accent-amber-light, #fbbf24)",
    "#d97706": "var(--color-accent-amber, #d97706)",
    "#b45309": "var(--color-accent-amber, #b45309)",
    "#f97316": "var(--color-accent-amber, #f97316)",
    "#ff9500": "var(--color-accent-amber, #ff9500)",
    "#eab308": "var(--color-accent-amber, #eab308)",
    "#f1c40f": "var(--color-accent-amber, #f1c40f)",
    "#ffd700": "var(--color-accent-amber, #ffd700)",
    "#92400e": "var(--color-accent-amber, #92400e)",
    "#fef3c7": "var(--color-warning-light, #fef3c7)",
    "#fffbeb": "var(--color-warning-light, #fffbeb)",
    "#22c55e": "var(--color-success, #22c55e)",
    "#16a34a": "var(--color-success, #16a34a)",
    "#15803d": "var(--color-success, #15803d)",
    "#34c759": "var(--color-success, #34c759)",
    "#166534": "var(--color-success, #166534)",
    "#f0fdf4": "var(--color-success-light, #f0fdf4)",
    "#ef4444": "var(--color-error, #ef4444)",
    "#dc2626": "var(--color-error, #dc2626)",
    "#b91c1c": "var(--color-error, #b91c1c)",
    "#f87171": "var(--color-error, #f87171)",
    "#e94560": "var(--color-error, #e94560)",
    "#ff6b6b": "var(--color-error, #ff6b6b)",
    "#dc3545": "var(--color-error, #dc3545)",
    "#991b1b": "var(--color-error, #991b1b)",
    "#fef2f2": "var(--color-error-light, #fef2f2)",
    "#fecaca": "var(--color-error-light, #fecaca)",
    "#fca5a5": "var(--color-error-light, #fca5a5)",
    "#8b5cf6": "var(--color-info, #8b5cf6)",
    "#a78bfa": "var(--color-info, #a78bfa)",
    "#7c3aed": "var(--color-info, #7c3aed)",
    "#635bff": "var(--color-info, #635bff)",
    "#8b7dff": "var(--color-info, #8b7dff)",
    "#d7d4f0": "var(--color-info-light, #d7d4f0)",
    "#e5e7eb": "var(--color-border-subtle, #e5e7eb)",
    "#e2e8f0": "var(--color-border-subtle, #e2e8f0)",
    "#d1d5db": "var(--color-border-default, #d1d5db)",
    "#cbd5e1": "var(--color-border-default, #cbd5e1)",
    "#e0e0e0": "var(--color-border-subtle, #e0e0e0)",
    "#07131b": "var(--color-bg-base, #07131b)",
    "#252525": "var(--color-bg-base, #252525)",
    "#1f1f1f": "var(--color-bg-base, #1f1f1f)",
    "#0000ff": "var(--color-accent-blue, #0000ff)",
    "#0000cc": "var(--color-accent-blue, #0000cc)",
    "#007bff": "var(--color-accent-blue, #007bff)",
    "#1976d2": "var(--color-accent-blue, #1976d2)",
    "#ecfdf5": "var(--color-success-light, #ecfdf5)",
    "#dcfce7": "var(--color-success-light, #dcfce7)",
    "#0ea574": "var(--color-accent-teal, #0ea574)",
    "#00897b": "var(--color-accent-teal, #00897b)",
    "#e67e22": "var(--color-accent-amber, #e67e22)",
    "#ff9800": "var(--color-accent-amber, #ff9800)",
    "#ff6b00": "var(--color-accent-amber, #ff6b00)",
    "#ffe066": "var(--color-accent-amber-light, #ffe066)",
    "#ff4444": "var(--color-error, #ff4444)",
    "#e53935": "var(--color-error, #e53935)",
    "#7b1fa2": "var(--color-info, #7b1fa2)",
    "#6f4e37": "var(--color-accent-amber, #6f4e37)",
    "#5d4037": "var(--color-accent-amber, #5d4037)",
    "#455a64": "var(--color-text-muted, #455a64)",
    "#607d8b": "var(--color-text-tertiary, #607d8b)",
    "#d32f2f": "var(--color-error, #d32f2f)",
    "#dd4444": "var(--color-error, #dd4444)",
    "#ff0000": "var(--color-error, #ff0000)",
    "#2e7d32": "var(--color-success, #2e7d32)",
    "#009900": "var(--color-success, #009900)",
    "#77ee77": "var(--color-success-light, #77ee77)",
    "#225a7e": "var(--color-accent-blue, #225a7e)",
    "#0ea573": "var(--color-accent-teal, #0ea573)",
    "#132638": "var(--color-bg-base, #132638)",
    "#af52de": "var(--color-info, #af52de)",
    "#dddddd": "var(--color-border-subtle, #dddddd)",
    "#d9d9d9": "var(--color-border-subtle, #d9d9d9)",
    "#d4d4d4": "var(--color-border-default, #d4d4d4)",
    "#c0c0c0": "var(--color-text-secondary, #c0c0c0)",
    "#a0a0a0": "var(--color-text-muted, #a0a0a0)",
    "#e5e5e5": "var(--color-border-subtle, #e5e5e5)",
    "#e9ecef": "var(--color-border-subtle, #e9ecef)",
    "#e8ecf0": "var(--color-border-subtle, #e8ecf0)",
    "#f7f7f7": "var(--color-bg-muted, #f7f7f7)",
    "#f9f9f9": "var(--color-bg-muted, #f9f9f9)",
    "#fafafa": "var(--color-bg-muted, #fafafa)",
    "#f5f5f5": "var(--color-bg-muted, #f5f5f5)",
    "#0f0f1a": "var(--color-bg-base, #0f0f1a)",
    "#111111": "var(--color-bg-base, #111111)",
    "#1c1c1c": "var(--color-bg-base, #1c1c1c)",
    "#0d0d0d": "var(--color-bg-base, #0d0d0d)",
    "#0a0a0a": "var(--color-bg-base, #0a0a0a)",
    "#1a1a2e": "var(--color-bg-elevated, #1a1a2e)",
    "#1a2634": "var(--color-bg-base, #1a2634)",
    "#122333": "var(--color-bg-base, #122333)",
    "#0f1f35": "var(--color-bg-base, #0f1f35)",
    "#0a1420": "var(--color-bg-base, #0a1420)",
    "#2d3a47": "var(--color-bg-elevated, #2d3a47)",
    "#444444": "var(--color-text-muted, #444444)",
    "#28a745": "var(--color-success, #28a745)",
    "#218838": "var(--color-success, #218838)",
    "#27ae60": "var(--color-success, #27ae60)",
    "#4ade80": "var(--color-success-light, #4ade80)",
    "#a7f3d0": "var(--color-success-light, #a7f3d0)",
    "#bbf7d0": "var(--color-success-light, #bbf7d0)",
    "#d4edda": "var(--color-success-light, #d4edda)",
    "#c3e6cb": "var(--color-success-light, #c3e6cb)",
    "#065f46": "var(--color-success, #065f46)",
    "#155724": "var(--color-success, #155724)",
    "#0d9669": "var(--color-accent-teal, #0d9669)",
    "#c82333": "var(--color-error, #c82333)",
    "#cc0000": "var(--color-error, #cc0000)",
    "#ff3b30": "var(--color-error, #ff3b30)",
    "#ff6666": "var(--color-error, #ff6666)",
    "#721c24": "var(--color-error, #721c24)",
    "#f8d7da": "var(--color-error-light, #f8d7da)",
    "#f5c6cb": "var(--color-error-light, #f5c6cb)",
    "#fee2e2": "var(--color-error-light, #fee2e2)",
    "#c4b5fd": "var(--color-info-light, #c4b5fd)",
    "#c084fc": "var(--color-info, #c084fc)",
    "#6d28d9": "var(--color-info, #6d28d9)",
    "#9b59b6": "var(--color-info, #9b59b6)",
    "#ec4899": "var(--color-accent-pink, #ec4899)",
    "#db2777": "var(--color-accent-pink, #db2777)",
    "#2a6d94": "var(--color-accent-blue, #2a6d94)",
    "#0f3347": "var(--color-accent-blue, #0f3347)",
    "#0f3a54": "var(--color-accent-blue, #0f3a54)",
    "#0056b3": "var(--color-accent-blue, #0056b3)",
    "#0055aa": "var(--color-accent-blue, #0055aa)",
    "#3498db": "var(--color-accent-blue, #3498db)",
    "#22d3ee": "var(--color-accent-teal-light, #22d3ee)",
    "#5ac8fa": "var(--color-accent-teal-light, #5ac8fa)",
    "#0891b2": "var(--color-accent-teal, #0891b2)",
    "#1abc9c": "var(--color-accent-teal, #1abc9c)",
    "#1877f2": "var(--color-brand-facebook, #1877f2)",
    "#0077b5": "var(--color-brand-linkedin, #0077b5)",
    "#a8cc00": "var(--color-accent-lime-dark, #a8cc00)",
    "#c3ea00": "var(--color-accent-lime, #c3ea00)",
    "#c4ed00": "var(--color-accent-lime, #c4ed00)",
    "#e5c158": "var(--color-accent-amber, #e5c158)",
    "#e6b84d": "var(--color-accent-amber, #e6b84d)",
    "#c49a3a": "var(--color-accent-amber, #c49a3a)",
    "#cd7f32": "var(--color-accent-amber, #cd7f32)",
    "#b06b28": "var(--color-accent-amber, #b06b28)",
    "#a16207": "var(--color-accent-amber, #a16207)",
    "#78350f": "var(--color-accent-amber, #78350f)",
    "#c2410c": "var(--color-accent-amber, #c2410c)",
    "#f39c12": "var(--color-accent-amber, #f39c12)",
    "#ffcc00": "var(--color-accent-amber, #ffcc00)",
    "#f0d060": "var(--color-accent-amber-light, #f0d060)",
    "#f6e7c7": "var(--color-accent-amber-light, #f6e7c7)",
    "#8b7355": "var(--color-accent-amber, #8b7355)",
    "#e8f2ff": "var(--color-accent-blue-light, #e8f2ff)",
    "#eff6ff": "var(--color-accent-blue-light, #eff6ff)",
    "#f0f7ff": "var(--color-accent-blue-light, #f0f7ff)",
    "#e8f4f8": "var(--color-accent-blue-light, #e8f4f8)",
    "#d0e3ed": "var(--color-accent-blue-light, #d0e3ed)",
    "#229922": "var(--color-code-green, #229922)",
    "#117700": "var(--color-code-green, #117700)",
    "#116644": "var(--color-code-green, #116644)",
    "#008855": "var(--color-code-green, #008855)",
    "#00bb00": "var(--color-code-green, #00bb00)",
    "#770088": "var(--color-code-purple, #770088)",
    "#3300aa": "var(--color-code-purple, #3300aa)",
    "#221199": "var(--color-code-blue, #221199)",
    "#aa5500": "var(--color-code-orange, #aa5500)",
    "#ff5500": "var(--color-code-orange, #ff5500)",
    "#aa1111": "var(--color-code-red, #aa1111)",
    "#aa2222": "var(--color-code-red, #aa2222)",
    "#999977": "var(--color-code-comment, #999977)",
    "#ffffaa": "var(--color-code-highlight, #ffffaa)",
    "#d4a84b": "var(--color-accent-amber, #d4a84b)",
    "#c9a048": "var(--color-accent-amber, #c9a048)",
    "#b8962f": "var(--color-accent-amber, #b8962f)"
  }
}
